setup.py
eventsource/__init__.py
eventsource/client.py
eventsource/listener.py
eventsource/request.py
eventsource.egg-info/PKG-INFO
eventsource.egg-info/SOURCES.txt
eventsource.egg-info/dependency_links.txt
eventsource.egg-info/entry_points.txt
eventsource.egg-info/not-zip-safe
eventsource.egg-info/requires.txt
eventsource.egg-info/top_level.txt