Metadata-Version: 1.0
Name: eventsource
Version: 1.1.1
Summary: Event Source Library
Home-page: http://packages.python.org/eventsource/
Author: Bernard Pratz
Author-email: guyzmo@hackable-devices.org
License: GPLv3
Platform: UNKNOWN
Classifier: Topic :: Internet :: WWW/HTTP :: Dynamic Content
Classifier: Intended Audience :: Developers
Classifier: License :: OSI Approved :: GNU General Public License v3 (GPLv3)
Classifier: Operating System :: OS Independent
Classifier: Programming Language :: Python
Classifier: Topic :: Utilities
